factor_expr/__init__.py
factor_expr/_lib.cp312-win_amd64.pyd
factor_expr/replay.py
factor_expr/tests/__init__.py
factor_expr/tests/factors/__init__.py
factor_expr/tests/factors/test_arithmetic.py
factor_expr/tests/factors/test_logic.py
factor_expr/tests/factors/test_sanity.py
factor_expr/tests/factors/test_window.py
factor_expr-0.3.0.dist-info/METADATA
factor_expr-0.3.0.dist-info/WHEEL
factor_expr-0.3.0.dist-info/RECORD
