Metadata-Version: 2.1
Name: factor_expr
Version: 0.3.0
Summary: Extreme fast factor expression & computation library for Python.
License: MIT
Keywords: factor,expression,alpha,S-expression,quantative trading,trading,algotrading
Author: Weiyuan Wu
Author-email: youngw@sfu.ca
Requires-Python: >=3.11,<4.0
Classifier: Development Status :: 4 - Beta
Classifier: Environment :: Console
Classifier: Intended Audience :: Developers
Classifier: Intended Audience :: Financial and Insurance Industry
Classifier: Intended Audience :: Science/Research
Classifier: License :: OSI Approved :: MIT License
Classifier: Operating System :: OS Independent
Classifier: Programming Language :: Python :: 3
Classifier: Programming Language :: Python :: 3.11
Classifier: Programming Language :: Python :: 3.12
Classifier: Topic :: Scientific/Engineering
Classifier: Topic :: Software Development :: Build Tools
Requires-Dist: numpy (>=1.26,<2.0)
Requires-Dist: pyarrow[cffi] (>=15.0.0,<16.0.0)
Requires-Dist: tqdm (>=4,<5)
